pyjamfpro/__init__.py
pyjamfpro/endpoints.py
pyjamfpro/jamfpro.py
pyjamfpro/utils/__init__.py
pyjamfpro/utils/dict_to_xml.py
pyjamfpro-0.2.1.dist-info/LICENSE.md
pyjamfpro-0.2.1.dist-info/METADATA
pyjamfpro-0.2.1.dist-info/WHEEL
pyjamfpro-0.2.1.dist-info/top_level.txt
pyjamfpro-0.2.1.dist-info/RECORD
