Metadata-Version: 2.1
Name: pyjamfpro
Version: 0.2.1
Summary: Synchronous client for Jamf Classic/Pro API
Home-page: https://github.com/dougpenny/PyJamfPro
Author: Doug Penny
Author-email: dpenny@icloud.com
Project-URL: Bug Tracker, https://github.com/dougpenny/PyJamfPro/issues
Classifier: Programming Language :: Python :: 3
Classifier: Programming Language :: Python :: 3 :: Only
Classifier: Programming Language :: Python :: 3.8
Classifier: Programming Language :: Python :: 3.9
Classifier: Programming Language :: Python :: 3.10
Classifier: Programming Language :: Python :: 3.11
Classifier: Programming Language :: Python :: 3.12
Classifier: License :: OSI Approved :: MIT License
Classifier: Operating System :: OS Independent
Requires-Python: >=3.8
License-File: LICENSE.md
Requires-Dist: requests>=2.32.3
